nnodes/__init__.py
nnodes/directory.py
nnodes/job.py
nnodes/mpi.py
nnodes/mpiexec.py
nnodes/node.py
nnodes/root.py
nnodes/tests.py
nnodes-0.0.2.dist-info/LICENSE
nnodes-0.0.2.dist-info/METADATA
nnodes-0.0.2.dist-info/WHEEL
nnodes-0.0.2.dist-info/top_level.txt
nnodes-0.0.2.dist-info/RECORD
